[{"line":1,"elements":[{"start_timestamp":"2025-03-21T17:44:49.444Z","line":3,"name":"validate Google search functionality","description":"","id":"search-google-functionality;validate-google-search-functionality","type":"scenario","keyword":"Scenario","steps":[{"result":{"error_message":"java.lang.NoClassDefFoundError: org/apache/logging/log4j/util/Lazy\r\n\tat org.apache.logging.log4j.core.selector.ClassLoaderContextSelector.<init>(ClassLoaderContextSelector.java:55)\r\n\tat org.apache.logging.log4j.core.impl.Log4jContextFactory.createContextSelector(Log4jContextFactory.java:108)\r\n\tat org.apache.logging.log4j.core.impl.Log4jContextFactory.<init>(Log4jContextFactory.java:60)\r\n\tat java.base/jdk.internal.reflect.DirectConstructorHandleAccessor.newInstance(DirectConstructorHandleAccessor.java:62)\r\n\tat java.base/java.lang.reflect.Constructor.newInstanceWithCaller(Constructor.java:502)\r\n\tat java.base/java.lang.reflect.ReflectAccess.newInstance(ReflectAccess.java:128)\r\n\tat java.base/jdk.internal.reflect.ReflectionFactory.newInstance(ReflectionFactory.java:304)\r\n\tat java.base/java.lang.Class.newInstance(Class.java:725)\r\n\tat org.apache.logging.log4j.LogManager.<clinit>(LogManager.java:95)\r\n\tat teststeps.SunSteps.user_launch_a_chrome_browser(SunSteps.java:28)\r\n\tat ✽.user launch a chrome browser(file:///C:/Users/lppaw/Desktop/cucumber%202/cucumbber/FeatureFile/suncorp.feature:4)\r\nCaused by: java.lang.ClassNotFoundException: org.apache.logging.log4j.util.Lazy\r\n\tat java.base/jdk.internal.loader.BuiltinClassLoader.loadClass(BuiltinClassLoader.java:641)\r\n\tat java.base/jdk.internal.loader.ClassLoaders$AppClassLoader.loadClass(ClassLoaders.java:188)\r\n\tat java.base/java.lang.ClassLoader.loadClass(ClassLoader.java:526)\r\n\tat org.apache.logging.log4j.core.selector.ClassLoaderContextSelector.<init>(ClassLoaderContextSelector.java:55)\r\n\tat org.apache.logging.log4j.core.impl.Log4jContextFactory.createContextSelector(Log4jContextFactory.java:108)\r\n\tat org.apache.logging.log4j.core.impl.Log4jContextFactory.<init>(Log4jContextFactory.java:60)\r\n\tat java.base/jdk.internal.reflect.DirectConstructorHandleAccessor.newInstance(DirectConstructorHandleAccessor.java:62)\r\n\tat java.base/java.lang.reflect.Constructor.newInstanceWithCaller(Constructor.java:502)\r\n\tat java.base/java.lang.reflect.ReflectAccess.newInstance(ReflectAccess.java:128)\r\n\tat java.base/jdk.internal.reflect.ReflectionFactory.newInstance(ReflectionFactory.java:304)\r\n\tat java.base/java.lang.Class.newInstance(Class.java:725)\r\n\tat org.apache.logging.log4j.LogManager.<clinit>(LogManager.java:95)\r\n\tat teststeps.SunSteps.user_launch_a_chrome_browser(SunSteps.java:28)\r\n\tat java.base/jdk.internal.reflect.DirectMethodHandleAccessor.invoke(DirectMethodHandleAccessor.java:103)\r\n\tat java.base/java.lang.reflect.Method.invoke(Method.java:580)\r\n\tat io.cucumber.java.Invoker.doInvoke(Invoker.java:66)\r\n\tat io.cucumber.java.Invoker.invoke(Invoker.java:24)\r\n\tat io.cucumber.java.AbstractGlueDefinition.invokeMethod(AbstractGlueDefinition.java:47)\r\n\tat io.cucumber.java.JavaStepDefinition.execute(JavaStepDefinition.java:29)\r\n\tat io.cucumber.core.runner.CoreStepDefinition.execute(CoreStepDefinition.java:66)\r\n\tat io.cucumber.core.runner.PickleStepDefinitionMatch.runStep(PickleStepDefinitionMatch.java:62)\r\n\tat io.cucumber.core.runner.ExecutionMode$1.execute(ExecutionMode.java:10)\r\n\tat io.cucumber.core.runner.TestStep.executeStep(TestStep.java:81)\r\n\tat io.cucumber.core.runner.TestStep.run(TestStep.java:53)\r\n\tat io.cucumber.core.runner.PickleStepTestStep.run(PickleStepTestStep.java:51)\r\n\tat io.cucumber.core.runner.TestCase.run(TestCase.java:84)\r\n\tat io.cucumber.core.runner.Runner.runPickle(Runner.java:75)\r\n\tat io.cucumber.junit.PickleRunners$NoStepDescriptions.lambda$run$0(PickleRunners.java:151)\r\n\tat io.cucumber.core.runtime.CucumberExecutionContext.lambda$runTestCase$5(CucumberExecutionContext.java:136)\r\n\tat io.cucumber.core.runtime.RethrowingThrowableCollector.executeAndThrow(RethrowingThrowableCollector.java:23)\r\n\tat io.cucumber.core.runtime.CucumberExecutionContext.runTestCase(CucumberExecutionContext.java:136)\r\n\tat io.cucumber.junit.PickleRunners$NoStepDescriptions.run(PickleRunners.java:148)\r\n\tat io.cucumber.junit.FeatureRunner.runChild(FeatureRunner.java:144)\r\n\tat io.cucumber.junit.FeatureRunner.runChild(FeatureRunner.java:28)\r\n\tat org.junit.runners.ParentRunner$4.run(ParentRunner.java:331)\r\n\tat org.junit.runners.ParentRunner$1.schedule(ParentRunner.java:79)\r\n\tat org.junit.runners.ParentRunner.runChildren(ParentRunner.java:329)\r\n\tat org.junit.runners.ParentRunner.access$100(ParentRunner.java:66)\r\n\tat org.junit.runners.ParentRunner$2.evaluate(ParentRunner.java:293)\r\n\tat org.junit.runners.ParentRunner$3.evaluate(ParentRunner.java:306)\r\n\tat org.junit.runners.ParentRunner.run(ParentRunner.java:413)\r\n\tat io.cucumber.junit.FeatureRunner.run(FeatureRunner.java:137)\r\n\tat io.cucumber.junit.Cucumber.runChild(Cucumber.java:199)\r\n\tat io.cucumber.junit.Cucumber.runChild(Cucumber.java:89)\r\n\tat org.junit.runners.ParentRunner$4.run(ParentRunner.java:331)\r\n\tat org.junit.runners.ParentRunner$1.schedule(ParentRunner.java:79)\r\n\tat org.junit.runners.ParentRunner.runChildren(ParentRunner.java:329)\r\n\tat org.junit.runners.ParentRunner.access$100(ParentRunner.java:66)\r\n\tat org.junit.runners.ParentRunner$2.evaluate(ParentRunner.java:293)\r\n\tat io.cucumber.core.runtime.CucumberExecutionContext.lambda$runFeatures$6(CucumberExecutionContext.java:147)\r\n\tat io.cucumber.core.runtime.CucumberExecutionContext.execute(CucumberExecutionContext.java:162)\r\n\tat io.cucumber.core.runtime.CucumberExecutionContext.runFeatures(CucumberExecutionContext.java:145)\r\n\tat io.cucumber.junit.Cucumber$StartAndFinishTestRun.evaluate(Cucumber.java:229)\r\n\tat org.junit.runners.ParentRunner$3.evaluate(ParentRunner.java:306)\r\n\tat org.junit.runners.ParentRunner.run(ParentRunner.java:413)\r\n\tat org.eclipse.jdt.internal.junit4.runner.JUnit4TestReference.run(JUnit4TestReference.java:93)\r\n\tat org.eclipse.jdt.internal.junit.runner.TestExecution.run(TestExecution.java:40)\r\n\tat org.eclipse.jdt.internal.junit.runner.RemoteTestRunner.runTests(RemoteTestRunner.java:530)\r\n\tat org.eclipse.jdt.internal.junit.runner.RemoteTestRunner.runTests(RemoteTestRunner.java:758)\r\n\tat org.eclipse.jdt.internal.junit.runner.RemoteTestRunner.run(RemoteTestRunner.java:453)\r\n\tat org.eclipse.jdt.internal.junit.runner.RemoteTestRunner.main(RemoteTestRunner.java:211)\r\n","duration":117601600,"status":"failed"},"line":4,"name":"user launch a chrome browser","match":{"location":"teststeps.SunSteps.user_launch_a_chrome_browser()"},"keyword":"Given "},{"result":{"status":"skipped"},"line":5,"name":"user enter an URL as \"https://www.google.com/\"","match":{"arguments":[{"val":"\"https://www.google.com/\"","offset":21}],"location":"teststeps.SunSteps.user_enter_an_url_as(java.lang.String)"},"keyword":"When "},{"result":{"status":"skipped"},"line":6,"name":"enter a search text as \"https://www.facebook.com/login/\"","match":{"arguments":[{"val":"\"https://www.facebook.com/login/\"","offset":23}],"location":"teststeps.SunSteps.enter_a_search_text_as(java.lang.String)"},"keyword":"And "},{"result":{"status":"skipped"},"line":8,"name":"close browser","match":{"location":"teststeps.SunSteps.close_browser()"},"keyword":"And "}],"tags":[{"name":"@sanity"}]}],"name":"search google functionality","description":"","id":"search-google-functionality","keyword":"Feature","uri":"file:FeatureFile/suncorp.feature","tags":[]}]